LICENSE
README.md
setup.py
north_robots/__init__.py
north_robots/__version__.py
north_robots/components.py
north_robots/gui.py
north_robots/managers.py
north_robots/n9.py
north_robots/robot.py
north_robots/spin_coater.py
north_robots/tools.py
north_robots.egg-info/PKG-INFO
north_robots.egg-info/SOURCES.txt
north_robots.egg-info/dependency_links.txt
north_robots.egg-info/requires.txt
north_robots.egg-info/top_level.txt