Metadata-Version: 2.1
Name: north-robots
Version: 0.0.31
Summary: A high-level library for controlling and programming North robots
Home-page: https://gitlab.com/north-robotics/north_robots
Author: Sean Clark
Author-email: sclark@northrobotics.com
License: MIT
Platform: UNKNOWN
Requires-Python: >=3.6.0
License-File: LICENSE
